uhash/__init__.py
uhash/config.py
uhash/uhash.py
uhash-0.1.5.dist-info/LICENSE
uhash-0.1.5.dist-info/WHEEL
uhash-0.1.5.dist-info/METADATA
uhash-0.1.5.dist-info/RECORD
