Metadata-Version: 2.1
Name: uhash
Version: 0.1.5
Summary: 
Author: NamTH
Author-email: namth2302@gmail.com
Requires-Python: >=3.6.2,<4.0.0
Classifier: Programming Language :: Python :: 3
Classifier: Programming Language :: Python :: 3.10
Classifier: Programming Language :: Python :: 3.7
Classifier: Programming Language :: Python :: 3.8
Classifier: Programming Language :: Python :: 3.9
Requires-Dist: pycryptodome (==3.10.1)
